electronicparsers/__init__.py
electronicparsers/abacus/README.md
electronicparsers/abacus/__init__.py
electronicparsers/abacus/__main__.py
electronicparsers/abacus/nomad_plugin.yaml
electronicparsers/abacus/parser.py
electronicparsers/abacus/metainfo/__init__.py
electronicparsers/abacus/metainfo/abacus.py
electronicparsers/abinit/README.md
electronicparsers/abinit/__init__.py
electronicparsers/abinit/__main__.py
electronicparsers/abinit/nomad_plugin.yaml
electronicparsers/abinit/parser.py
electronicparsers/abinit/metainfo/__init__.py
electronicparsers/abinit/metainfo/abinit.py
electronicparsers/abinit/metainfo/abinit_autogenerated.py
electronicparsers/ams/README.md
electronicparsers/ams/__init__.py
electronicparsers/ams/__main__.py
electronicparsers/ams/nomad_plugin.yaml
electronicparsers/ams/parser.py
electronicparsers/ams/rkf.py
electronicparsers/ams/metainfo/__init__.py
electronicparsers/ams/metainfo/ams.py
electronicparsers/atk/README.md
electronicparsers/atk/__init__.py
electronicparsers/atk/__main__.py
electronicparsers/atk/nomad_plugin.yaml
electronicparsers/atk/parser.py
electronicparsers/atk/metainfo/__init__.py
electronicparsers/atk/metainfo/atk.py
electronicparsers/bigdft/README.md
electronicparsers/bigdft/__init__.py
electronicparsers/bigdft/__main__.py
electronicparsers/bigdft/nomad_plugin.yaml
electronicparsers/bigdft/parser.py
electronicparsers/bigdft/metainfo/__init__.py
electronicparsers/castep/README.md
electronicparsers/castep/__init__.py
electronicparsers/castep/__main__.py
electronicparsers/castep/nomad_plugin.yaml
electronicparsers/castep/parser.py
electronicparsers/castep/metainfo/__init__.py
electronicparsers/castep/metainfo/castep.py
electronicparsers/charmm/README.md
electronicparsers/charmm/__init__.py
electronicparsers/charmm/__main__.py
electronicparsers/charmm/nomad_plugin.yaml
electronicparsers/charmm/parser.py
electronicparsers/charmm/metainfo/__init__.py
electronicparsers/charmm/metainfo/charmm.py
electronicparsers/cp2k/README.md
nomad_parser_plugins_electronic-1.0.13.dist-info/licenses/LICENSE
nomad_parser_plugins_electronic-1.0.13.dist-info/METADATA
nomad_parser_plugins_electronic-1.0.13.dist-info/WHEEL
nomad_parser_plugins_electronic-1.0.13.dist-info/entry_points.txt
nomad_parser_plugins_electronic-1.0.13.dist-info/top_level.txt
nomad_parser_plugins_electronic-1.0.13.dist-info/RECORD
