Metadata-Version: 2.4
Name: nomad-parser-plugins-electronic
Version: 1.0.13
Summary: Collection of NOMAD parsers for electronic structure codes.
Author: The NOMAD Authors
License: 
Project-URL: homepage, https://github.com/nomad-coe/electronic-parsers
License-File: LICENSE
Requires-Dist: h5py>=3.6.0
Requires-Dist: lxml>=5.2
Requires-Dist: nomad-lab>=1.3.17
Requires-Dist: nomad-schema-plugin-simulation-workflow>=1.0.1
Requires-Dist: nomad-schema-plugin-run>=1.0.1
Requires-Dist: nomad-parser-plugins-simulation>=1.0.2
Requires-Dist: netcdf4<=1.7.2
Requires-Dist: pyyaml>=6.0
Requires-Dist: pydantic>=1.10.8
Requires-Dist: numpy
Provides-Extra: dev
Requires-Dist: astroid>=2.11.7; extra == "dev"
Requires-Dist: mypy>=1.15; extra == "dev"
Requires-Dist: pytest; extra == "dev"
Requires-Dist: pytest-timeout; extra == "dev"
Requires-Dist: pytest-cov; extra == "dev"
Requires-Dist: ruff; extra == "dev"
Requires-Dist: typing-extensions>=4.12; extra == "dev"
Provides-Extra: infrastructure
Requires-Dist: nomad-lab[infrastructure]>=1.3.10; extra == "infrastructure"
Dynamic: license-file
